{
	"credit": "Made with Blockbench",
	"texture_size": [64, 64],
	"textures": {
		"1": "bow_expansion:item/log",
		"2": "bow_expansion:item/stone",
		"3": "bow_expansion:item/chest",
		"4": "bow_expansion:item/copper_block",
		"particle": "bow_expansion:item/log"
	},
	"elements": [
		{
			"name": "body",
			"from": [-1, 0, -1],
			"to": [11, 6, 5],
			"rotation": {"angle": 0, "axis": "y", "origin": [-0.75, 3.25, 2]},
			"faces": {
				"north": {"uv": [6, 6, 10, 10], "texture": "#2"},
				"east": {"uv": [2.5, 6, 6.5, 10], "texture": "#2"},
				"south": {"uv": [6, 2.5, 10, 6.5], "texture": "#2"},
				"west": {"uv": [9.5, 6, 13.5, 10], "texture": "#2"},
				"up": {"uv": [6, 2.5, 10, 6.5], "texture": "#2"},
				"down": {"uv": [6, 9.5, 10, 13.5], "texture": "#2"}
			}
		},
		{
			"name": "chest",
			"from": [2, -2, -3],
			"to": [8, 4, 3],
			"rotation": {"angle": 0, "axis": "y", "origin": [-0.75, 3.25, 2]},
			"faces": {
				"north": {"uv": [6, 6, 10, 10], "texture": "#3"},
				"east": {"uv": [2.5, 6, 6.5, 10], "texture": "#3"},
				"south": {"uv": [6, 2.5, 10, 6.5], "texture": "#3"},
				"west": {"uv": [9.5, 6, 13.5, 10], "texture": "#3"},
				"up": {"uv": [6, 2.5, 10, 6.5], "texture": "#3"},
				"down": {"uv": [6, 9.5, 10, 13.5], "texture": "#3"}
			}
		},
		{
			"name": "plate_0",
			"from": [-3, -1, -2],
			"to": [-2, 7, 6],
			"rotation": {"angle": 0, "axis": "y", "origin": [-0.75, 3.25, 2]},
			"faces": {
				"north": {"uv": [14, 0, 16, 16], "texture": "#4"},
				"east": {"uv": [0, 0, 16, 16], "texture": "#4"},
				"south": {"uv": [14, 0, 16, 16], "texture": "#4"},
				"west": {"uv": [0, 0, 16, 16], "texture": "#4"},
				"up": {"uv": [14, 0, 16, 16], "texture": "#4"},
				"down": {"uv": [14, 0, 16, 16], "texture": "#4"}
			}
		},
		{
			"name": "plate_1",
			"from": [-15, -1, -2],
			"to": [-14, 7, 6],
			"rotation": {"angle": 0, "axis": "y", "origin": [-0.75, 3.25, 2]},
			"faces": {
				"north": {"uv": [14, 0, 16, 16], "texture": "#4"},
				"east": {"uv": [0, 0, 16, 16], "texture": "#4"},
				"south": {"uv": [14, 0, 16, 16], "texture": "#4"},
				"west": {"uv": [0, 0, 16, 16], "texture": "#4"},
				"up": {"uv": [14, 0, 16, 16], "texture": "#4"},
				"down": {"uv": [14, 0, 16, 16], "texture": "#4"}
			}
		},
		{
			"name": "cannon_0",
			"from": [-16, 4.90165, 1.17678],
			"to": [-3, 6.90165, 3.17678],
			"rotation": {"angle": 45, "axis": "x", "origin": [-0.75, 3.25, 2]},
			"faces": {
				"north": {"uv": [6.55263, 6.52632, 13.05263, 7.53947], "rotation": 180, "texture": "#2"},
				"east": {"uv": [6.55263, 6.52632, 13.05263, 7.53947], "texture": "#2"},
				"south": {"uv": [6.55263, 6.52632, 13.05263, 7.53947], "texture": "#2"},
				"west": {"uv": [9, 9, 10.5, 10.5], "texture": "#2"},
				"up": {"uv": [6.55263, 6.52632, 13.05263, 7.53947], "texture": "#2"},
				"down": {"uv": [6.55263, 6.52632, 13.05263, 7.53947], "texture": "#2"}
			}
		},
		{
			"name": "cannon_1",
			"from": [-16, 4.90165, 0.82322],
			"to": [-3, 6.90165, 2.82322],
			"rotation": {"angle": -45, "axis": "x", "origin": [-0.75, 3.25, 2]},
			"faces": {
				"north": {"uv": [6.55263, 6.52632, 13.05263, 7.53947], "rotation": 180, "texture": "#2"},
				"east": {"uv": [6.55263, 6.52632, 13.05263, 7.53947], "rotation": 270, "texture": "#2"},
				"south": {"uv": [6.55263, 6.52632, 13.05263, 7.53947], "texture": "#2"},
				"west": {"uv": [9, 9, 10.5, 10.5], "rotation": 90, "texture": "#2"},
				"up": {"uv": [6.55263, 6.52632, 13.05263, 7.53947], "texture": "#2"},
				"down": {"uv": [6.55263, 6.52632, 13.05263, 7.53947], "texture": "#2"}
			}
		},
		{
			"name": "cannon_2",
			"from": [-16, 2.07322, -2.0052],
			"to": [-3, 4.07322, -0.0052],
			"rotation": {"angle": -45, "axis": "x", "origin": [-0.75, 3.25, 2]},
			"faces": {
				"north": {"uv": [6.55263, 6.52632, 13.05263, 7.53947], "rotation": 180, "texture": "#2"},
				"east": {"uv": [6.55263, 6.52632, 13.05263, 7.53947], "texture": "#2"},
				"south": {"uv": [6.55263, 6.52632, 13.05263, 7.53947], "texture": "#2"},
				"west": {"uv": [9, 9, 10.5, 10.5], "texture": "#2"},
				"up": {"uv": [6.55263, 6.52632, 13.05263, 7.53947], "texture": "#2"},
				"down": {"uv": [6.55263, 6.52632, 13.05263, 7.53947], "texture": "#2"}
			}
		},
		{
			"name": "cannon_3",
			"from": [-16, -0.7552, 0.82322],
			"to": [-3, 1.2448, 2.82322],
			"rotation": {"angle": -45, "axis": "x", "origin": [-0.75, 3.25, 2]},
			"faces": {
				"north": {"uv": [6.55263, 6.52632, 13.05263, 7.53947], "rotation": 180, "texture": "#2"},
				"east": {"uv": [6.55263, 6.52632, 13.05263, 7.53947], "texture": "#2"},
				"south": {"uv": [6.55263, 6.52632, 13.05263, 7.53947], "texture": "#2"},
				"west": {"uv": [9, 9, 10.5, 10.5], "texture": "#2"},
				"up": {"uv": [6.55263, 6.52632, 13.05263, 7.53947], "texture": "#2"},
				"down": {"uv": [6.55263, 6.52632, 13.05263, 7.53947], "texture": "#2"}
			}
		},
		{
			"name": "bar_0",
			"from": [-15, 2, -3],
			"to": [-2, 4, -2],
			"rotation": {"angle": 0, "axis": "y", "origin": [-0.75, 3.25, 2]},
			"faces": {
				"north": {"uv": [0, 1, 16, 3], "texture": "#4"},
				"east": {"uv": [1, 6, 2, 8], "texture": "#4"},
				"south": {"uv": [0, 4, 16, 6], "texture": "#4"},
				"west": {"uv": [0, 6, 1, 8], "texture": "#4"},
				"up": {"uv": [16, 0.97, 0, 0], "texture": "#4"},
				"down": {"uv": [16, 3, 0, 4], "texture": "#4"}
			}
		},
		{
			"name": "bar_1",
			"from": [-15, 7, 1],
			"to": [-2, 8, 3],
			"rotation": {"angle": 0, "axis": "y", "origin": [-0.75, 3.25, 2]},
			"faces": {
				"north": {"uv": [0, 1.92, 16, 2.92], "texture": "#4"},
				"east": {"uv": [2, 6, 4, 7], "texture": "#4"},
				"south": {"uv": [0, 5, 16, 6], "texture": "#4"},
				"west": {"uv": [0, 6, 2, 7], "texture": "#4"},
				"up": {"uv": [16, 2, 0, 0], "texture": "#4"},
				"down": {"uv": [16, 3, 0, 5], "texture": "#4"}
			}
		},
		{
			"name": "bar_2",
			"from": [-15, -2, 1],
			"to": [-2, -1, 3],
			"rotation": {"angle": 0, "axis": "y", "origin": [-0.75, 3.25, 2]},
			"faces": {
				"north": {"uv": [0, 1.92, 16, 2.92], "texture": "#4"},
				"east": {"uv": [2, 6, 4, 7], "texture": "#4"},
				"south": {"uv": [0, 5, 16, 6], "texture": "#4"},
				"west": {"uv": [0, 6, 2, 7], "texture": "#4"},
				"up": {"uv": [16, 2, 0, 0], "texture": "#4"},
				"down": {"uv": [16, 3, 0, 5], "texture": "#4"}
			}
		},
		{
			"name": "bar_3",
			"from": [-15, 2, 6],
			"to": [-2, 4, 7],
			"rotation": {"angle": 0, "axis": "y", "origin": [-0.75, 3.25, 2]},
			"faces": {
				"north": {"uv": [0, 1, 16, 3], "texture": "#4"},
				"east": {"uv": [1, 6, 2, 8], "texture": "#4"},
				"south": {"uv": [0, 4, 16, 6], "texture": "#4"},
				"west": {"uv": [0, 6, 1, 8], "texture": "#4"},
				"up": {"uv": [16, 0.97, 0, 0], "texture": "#4"},
				"down": {"uv": [16, 3, 0, 4], "texture": "#4"}
			}
		},
		{
			"name": "connection",
			"from": [-2.9, 1, 0],
			"to": [-0.9, 5, 4],
			"rotation": {"angle": 0, "axis": "y", "origin": [-0.75, 3.25, 2]},
			"faces": {
				"north": {"uv": [0, 0, 4, 8], "texture": "#4"},
				"east": {"uv": [2, 4.5, 3, 5.5], "texture": "#4"},
				"south": {"uv": [12, 0, 16, 8], "texture": "#4"},
				"west": {"uv": [0, 9.5, 1, 10.5], "texture": "#4"},
				"up": {"uv": [4, 0, 8, 8], "texture": "#4"},
				"down": {"uv": [8, 0, 12, 8], "texture": "#4"}
			}
		},
		{
			"name": "handle_0",
			"from": [11, 3, 1],
			"to": [12, 5, 3],
			"rotation": {"angle": 0, "axis": "y", "origin": [-0.75, 3.25, 2]},
			"faces": {
				"north": {"uv": [10.5, 8.5, 11, 9.5], "texture": "#1"},
				"east": {"uv": [11, 6.5, 12, 7.5], "texture": "#1"},
				"south": {"uv": [10, 7.5, 10.5, 8.5], "texture": "#1"},
				"west": {"uv": [10, 6.5, 11, 7.5], "texture": "#1"},
				"up": {"uv": [10.5, 7.5, 11, 8.5], "texture": "#1"},
				"down": {"uv": [10, 8.5, 10.5, 9.5], "texture": "#1"}
			}
		},
		{
			"name": "handle_1",
			"from": [12, 3, 1],
			"to": [14, 7, 3],
			"rotation": {"angle": 0, "axis": "y", "origin": [-0.75, 3.25, 2]},
			"faces": {
				"north": {"uv": [3, 6.51316, 4, 8.51316], "texture": "#1"},
				"east": {"uv": [4, 6.5, 5, 8.5], "texture": "#1"},
				"south": {"uv": [5, 6.5, 6, 8.5], "texture": "#1"},
				"west": {"uv": [4, 6.5, 5, 8.5], "texture": "#1"},
				"up": {"uv": [4, 8.5, 5, 9.5], "texture": "#1"},
				"down": {"uv": [3, 8.5, 4, 9.5], "texture": "#1"}
			}
		},
		{
			"name": "handle_2",
			"from": [2, 7, 1],
			"to": [14, 9, 3],
			"rotation": {"angle": 0, "axis": "y", "origin": [-0.75, 3.25, 2]},
			"faces": {
				"north": {"uv": [6.5, 6.5, 7.5, 9.5], "rotation": 90, "texture": "#1"},
				"east": {"uv": [7.5, 6.5, 8.5, 7.5], "texture": "#1"},
				"south": {"uv": [8.5, 6.5, 9.5, 9.5], "rotation": 90, "texture": "#1"},
				"west": {"uv": [7.5, 7.5, 8.5, 8.5], "texture": "#1"},
				"up": {"uv": [7.5, 6.5, 8.5, 9.5], "rotation": 90, "texture": "#1"},
				"down": {"uv": [7.5, 6.5, 8.5, 9.5], "rotation": 90, "texture": "#1"}
			}
		},
		{
			"name": "handle_3",
			"from": [0, 6, 1],
			"to": [2, 9, 3],
			"rotation": {"angle": 0, "axis": "y", "origin": [-0.75, 3.25, 2]},
			"faces": {
				"north": {"uv": [6.5, 3, 7.5, 4.5], "texture": "#1"},
				"east": {"uv": [7.5, 3, 8.5, 4.5], "texture": "#1"},
				"south": {"uv": [8.5, 3, 9.5, 4.5], "texture": "#1"},
				"west": {"uv": [6.5, 4.5, 7.5, 6], "texture": "#1"},
				"up": {"uv": [8.5, 4.5, 9.5, 5.5], "texture": "#1"},
				"down": {"uv": [7.5, 4.5, 8.5, 5.5], "texture": "#1"}
			}
		}
	],
	"display": {
		"thirdperson_righthand": {
			"rotation": [55, -90, 55],
			"translation": [-4.75, -2.5, 5],
			"scale": [0.66, 0.66, 0.66]
		},
		"thirdperson_lefthand": {
			"rotation": [-90, 89, 90],
			"translation": [5.75, -2.25, 3.25]
		},
		"firstperson_righthand": {
			"rotation": [18, -90, 5.31],
			"translation": [-14.87, -0.8, 5.13],
			"scale": [0.99, 0.99, 0.99]
		},
		"ground": {
			"translation": [8.5, 5.5, 6]
		},
		"gui": {
			"rotation": [34, 145, 0],
			"translation": [-2.5, 4.5, 0],
			"scale": [0.58, 0.58, 0.58]
		},
		"fixed": {
			"translation": [7.25, 4, 5.25],
			"scale": [0.82, 0.82, 0.82]
		}
	},
	"groups": [
		{
			"name": "machine_gun",
			"origin": [0, 0, 0],
			"color": 0,
			"children": [
				{
					"name": "body",
					"origin": [3.03333, 2.33333, 1.33333],
					"color": 0,
					"children": [
						0,
						1,
						{
							"name": "gun_head",
							"origin": [-8.9, 3, 2],
							"color": 0,
							"children": [2, 3, 4, 5, 6, 7, 8, 9, 10, 11, 12]
						},
						{
							"name": "handle",
							"origin": [8.375, 6.125, 2],
							"color": 0,
							"children": [13, 14, 15, 16]
						}
					]
				}
			]
		}
	],
	"override": [
		{
			"predicate": {
				"minecraft:pulling": 1
			},
			"model": "tutorialmod:item/machien_gun"
		},
		{
			"predicate": {
				"minecraft:pulling": 1,
				"minecraft:pull": 0.9
			},
			"model": "tutorialmod:item/machien_gun"
		}
	]
}